odoo8_addon_web_hide_db_manager_link-8.0.1.0.0-py2.7-nspkg.pth
odoo_addons/web_hide_db_manager_link/__openerp__.py
odoo_addons/web_hide_db_manager_link/__init__.py
odoo_addons/web_hide_db_manager_link/README.rst
odoo_addons/web_hide_db_manager_link/views/webclient_templates.xml
odoo_addons/web_hide_db_manager_link/static/description/icon.svg
odoo_addons/web_hide_db_manager_link/static/description/icon.png
odoo_addons/web_hide_db_manager_link/static/src/img/screenshot.png
odoo8_addon_web_hide_db_manager_link-8.0.1.0.0.dist-info/top_level.txt
odoo8_addon_web_hide_db_manager_link-8.0.1.0.0.dist-info/WHEEL
odoo8_addon_web_hide_db_manager_link-8.0.1.0.0.dist-info/RECORD
odoo8_addon_web_hide_db_manager_link-8.0.1.0.0.dist-info/metadata.json
odoo8_addon_web_hide_db_manager_link-8.0.1.0.0.dist-info/DESCRIPTION.rst
odoo8_addon_web_hide_db_manager_link-8.0.1.0.0.dist-info/METADATA
odoo8_addon_web_hide_db_manager_link-8.0.1.0.0.dist-info/namespace_packages.txt
