Metadata-Version: 2.0
Name: odoo8-addon-web-hide-db-manager-link
Version: 8.0.1.0.0
Summary: Hide link to database manager in login screen
Home-page: http://anubia.es
Author: UNKNOWN
Author-email: UNKNOWN
License: AGPL-3
Platform: UNKNOWN
Requires-Dist: odoo (<9.0a,>=8.0a)
Classifier: Programming Language :: Python :: 2.7
Classifier: Framework :: Odoo
Classifier: License :: OSI Approved :: GNU Affero General Public License v3
